sforecast/__init__.py
sforecast/endogenous_transforms.py
sforecast/forecast_neural_networks.py
sforecast/sliding_forecast.py
sforecast-0.6.4.dist-info/LICENSE
sforecast-0.6.4.dist-info/WHEEL
sforecast-0.6.4.dist-info/METADATA
sforecast-0.6.4.dist-info/RECORD
