Metadata-Version: 2.1
Name: sforecast
Version: 0.6.4
Summary: A framework for running forecasting models within a sliding/expanding window out-of-sample forecast fit (train/test) and prediction (forecasts). The package includes support of classical forecasting models, SK Learn supervised learning ML models, and TensorFlow deep learning models.
License: MIT
Author: Alberto Gutierrez
Requires-Python: >=3.10,<3.13
Classifier: License :: OSI Approved :: MIT License
Classifier: Programming Language :: Python :: 3
Classifier: Programming Language :: Python :: 3.10
Requires-Dist: beautifulplots (>=0.2.6)
Requires-Dist: numpy (>=1.21.2,<2.0.0)
Requires-Dist: pandas (>=1.4.0)
Requires-Dist: pmdarima (>=1.8.0)
Requires-Dist: regex (>=2024.5.15,<2025.0.0)
Requires-Dist: scikit-learn (>=1.4.2)
Requires-Dist: scipy (>=1.13.1,<2.0.0)
Requires-Dist: statsmodels (>=0.13.2)
Requires-Dist: tensorflow (>2.8.0,<=2.11)
Requires-Dist: xgboost (>=2.0.3)
